dataer_tool/__init__.py
dataer_tool/_nbdev.py
dataer_tool/core.py
dataer_tool/imports.py
dataer_tool/utils.py
dataer_tool/simulate/__init__.py
dataer_tool/simulate/user.py
dataer_tool/visualize/__init__.py
dataer_tool/visualize/bokeh.py
dataer_tool-0.0.4.dist-info/LICENSE
dataer_tool-0.0.4.dist-info/METADATA
dataer_tool-0.0.4.dist-info/WHEEL
dataer_tool-0.0.4.dist-info/entry_points.txt
dataer_tool-0.0.4.dist-info/top_level.txt
dataer_tool-0.0.4.dist-info/RECORD
