Metadata-Version: 2.1
Name: dataer-tool
Version: 0.0.4
Summary: UNKNOWN
Home-page: https://github.com/JunxinGao/dataer_tool/tree/master/
Author: Junxin Gao
Author-email: junxin.gao@outlook.com
License: Apache Software License 2.0
Keywords: dataer_tool
Platform: UNKNOWN
Classifier: Development Status :: 3 - Alpha
Classifier: Intended Audience :: Developers
Classifier: Natural Language :: English
Classifier: Programming Language :: Python :: 3.6
Classifier: Programming Language :: Python :: 3.7
Classifier: Programming Language :: Python :: 3.8
Classifier: License :: OSI Approved :: Apache Software License
Requires-Python: >=3.6
Requires-Dist: loguru
Requires-Dist: awswrangler
Requires-Dist: bokeh
Requires-Dist: pandas
Requires-Dist: numpy
